stockai/__init__.py
stockai/client.py
stockai_sdk-1.0.0.dist-info/METADATA
stockai_sdk-1.0.0.dist-info/WHEEL
stockai_sdk-1.0.0.dist-info/top_level.txt
stockai_sdk-1.0.0.dist-info/RECORD
