Metadata-Version: 2.4
Name: stockai-sdk
Version: 1.0.0
Summary: SDK for Stock AI Protected Endpoints
Author: Stock AI Dev
Requires-Dist: requests
Dynamic: author
Dynamic: requires-dist
Dynamic: summary
